openap/__init__.py
openap/drag.py
openap/fuel.py
openap/kinematic.py
openap/phase.py
openap/prop.py
openap/thrust.py
openap/data/.gitignore
openap/data/LICENSE
openap/data/aircraft/a319.yml
openap/data/aircraft/a320.yml
openap/data/aircraft/a321.yml
openap/data/aircraft/a332.yml
openap/data/aircraft/a333.yml
openap/data/aircraft/a343.yml
openap/data/aircraft/a359.yml
openap/data/aircraft/a388.yml
openap/data/aircraft/b734.yml
openap/data/aircraft/b737.yml
openap/data/aircraft/b738.yml
openap/data/aircraft/b739.yml
openap/data/aircraft/b744.yml
openap/data/aircraft/b748.yml
openap/data/aircraft/b752.yml
openap/data/aircraft/b763.yml
openap/data/aircraft/b772.yml
openap/data/aircraft/b773.yml
openap/data/aircraft/b77w.yml
openap/data/aircraft/b788.yml
openap/data/aircraft/b789.yml
openap/data/aircraft/c550.yml
openap/data/aircraft/e145.yml
openap/data/aircraft/e170.yml
openap/data/aircraft/e190.yml
openap/data/aircraft/e195.yml
openap/data/aircraft/e75l.yml
openap/data/dragpolar/a319.yml
openap/data/dragpolar/a320.yml
openap/data/dragpolar/a321.yml
openap/data/dragpolar/a332.yml
openap/data/dragpolar/a333.yml
openap/data/dragpolar/a359.yml
openap/data/dragpolar/a388.yml
openap/data/dragpolar/b734.yml
openap/data/dragpolar/b737.yml
openap/data/dragpolar/b738.yml
openap/data/dragpolar/b739.yml
openap/data/dragpolar/b744.yml
openap/data/dragpolar/b748.yml
openap/data/dragpolar/b772.yml
openap/data/dragpolar/b77w.yml
openap/data/dragpolar/b788.yml
openap/data/dragpolar/b789.yml
openap/data/dragpolar/c550.yml
openap/data/dragpolar/e190.yml
openap/data/dragpolar/e195.yml
openap/data/dragpolar/e75l.yml
openap/data/engine/engines.txt
openap/data/nav/airports.csv
openap/data/nav/fix.dat
openap/data/nav/nav.dat
openap/data/wrap/a319.txt
openap/data/wrap/a320.txt
openap/data/wrap/a321.txt
openap/data/wrap/a332.txt
openap/data/wrap/a333.txt
openap/data/wrap/a343.txt
openap/data/wrap/a388.txt
openap/data/wrap/b737.txt
openap/data/wrap/b738.txt
openap/data/wrap/b739.txt
openap1-1.0.dev1.dist-info/LICENSE
openap1-1.0.dev1.dist-info/METADATA
openap1-1.0.dev1.dist-info/WHEEL
openap1-1.0.dev1.dist-info/top_level.txt
openap1-1.0.dev1.dist-info/RECORD
