Metadata-Version: 2.1
Name: openap1
Version: 1.0.dev1
Summary: Open Aircraft Performance Model (OpenAP) in Python
Home-page: UNKNOWN
Author: Ashrith Appani
Author-email: ashrith.appani@rockwellcollins.com
License: GNU GPL v3
Keywords: OpenAP,Open Aircraft Performance,Open Data
Platform: UNKNOWN
Classifier: Development Status :: 3 - Alpha
Classifier: Intended Audience :: Developers
Classifier: Topic :: Software Development :: Build Tools
Classifier: License :: OSI Approved :: MIT License
Classifier: Programming Language :: Python :: 2
Classifier: Programming Language :: Python :: 2.6
Classifier: Programming Language :: Python :: 2.7
Classifier: Programming Language :: Python :: 3
Classifier: Programming Language :: Python :: 3.3
Classifier: Programming Language :: Python :: 3.4
Classifier: Programming Language :: Python :: 3.5
Classifier: Programming Language :: Python :: 3.6
Classifier: Programming Language :: Python :: 3.7
Requires-Dist: numpy
Requires-Dist: scipy
Requires-Dist: scikit-fuzzy
Requires-Dist: pandas
Requires-Dist: pyyaml
